vagx/__init__.py
vagx-0.0.1.dist-info/METADATA
vagx-0.0.1.dist-info/WHEEL
vagx-0.0.1.dist-info/RECORD
