Metadata-Version: 2.1
Name: vagx
Version: 0.0.1
Summary: Serverless platform for LLMs
Author: vagrant.ai
Requires-Python: >=3.10,<4.0
Classifier: Programming Language :: Python :: 3
Classifier: Programming Language :: Python :: 3.10
Classifier: Programming Language :: Python :: 3.11
